tfd_utils/__init__.py
tfd_utils/cli.py
tfd_utils/py.typed
tfd_utils/random_access.py
tfd_utils/pb2/__init__.py
tfd_utils/pb2/example.proto
tfd_utils/pb2/example_pb2.py
tfd_utils/pb2/example_pb2.pyi
tfd_utils/pb2/feature.proto
tfd_utils/pb2/feature_pb2.py
tfd_utils/pb2/feature_pb2.pyi
tfd_utils/writer/__init__.py
tfd_utils/writer/tf_writer.py
tfd_utils-0.3.0.dist-info/METADATA
tfd_utils-0.3.0.dist-info/WHEEL
tfd_utils-0.3.0.dist-info/entry_points.txt
tfd_utils-0.3.0.dist-info/licenses/LICENSE
tfd_utils-0.3.0.dist-info/RECORD
