Metadata-Version: 2.4
Name: tfd-utils
Version: 0.3.0
Summary: TensorFlow utilities for efficient TFRecord processing and random access
Author-email: Haobo Yuan <haoboyuan@ucmerced.edu>
License-File: LICENSE
Requires-Python: >=3.10
Requires-Dist: crc32c>=2.7.1
Requires-Dist: numpy>=1.25.0
Requires-Dist: protobuf<6.0.0.dev0,>=5.29.5
Provides-Extra: dev
Requires-Dist: pillow>=9.0.0; extra == 'dev'
Requires-Dist: pytest>=7.0.0; extra == 'dev'
Requires-Dist: requests>=2.25.0; extra == 'dev'
Requires-Dist: tensorflow>=2.19.0; extra == 'dev'
